{
  "source": "Synthetic (based on historical trends)",
  "period": {
    "start": "2021-11-01",
    "end": "2024-11-01",
    "years": 3
  },
  "indicators": 5,
  "datasets": [
    {
      "series": "FEDFUNDS",
      "name": "Federal Funds Rate",
      "unit": "Percent",
      "frequency": "monthly",
      "startValue": 0.25,
      "endValue": 5.5,
      "data": [
        {
          "date": "2021-11-01",
          "timestamp": 1635724800000,
          "value": 0.24
        },
        {
          "date": "2021-12-01",
          "timestamp": 1638316800000,
          "value": 0.29
        },
        {
          "date": "2022-01-01",
          "timestamp": 1640995200000,
          "value": -0.26
        },
        {
          "date": "2022-02-01",
          "timestamp": 1643673600000,
          "value": 0.53
        },
        {
          "date": "2022-03-01",
          "timestamp": 1646092800000,
          "value": 1.04
        },
        {
          "date": "2022-04-01",
          "timestamp": 1648771200000,
          "value": 1.96
        },
        {
          "date": "2022-05-01",
          "timestamp": 1651363200000,
          "value": 0.62
        },
        {
          "date": "2022-06-01",
          "timestamp": 1654041600000,
          "value": 1.93
        },
        {
          "date": "2022-07-01",
          "timestamp": 1656633600000,
          "value": 0.82
        },
        {
          "date": "2022-08-01",
          "timestamp": 1659312000000,
          "value": 2
        },
        {
          "date": "2022-09-01",
          "timestamp": 1661990400000,
          "value": 0.76
        },
        {
          "date": "2022-10-01",
          "timestamp": 1664582400000,
          "value": 2.25
        },
        {
          "date": "2022-11-01",
          "timestamp": 1667260800000,
          "value": 1.4
        },
        {
          "date": "2022-12-01",
          "timestamp": 1669852800000,
          "value": 3.1
        },
        {
          "date": "2023-01-01",
          "timestamp": 1672531200000,
          "value": 2.68
        },
        {
          "date": "2023-02-01",
          "timestamp": 1675209600000,
          "value": 2.54
        },
        {
          "date": "2023-03-01",
          "timestamp": 1677628800000,
          "value": 3.12
        },
        {
          "date": "2023-04-01",
          "timestamp": 1680307200000,
          "value": 3.42
        },
        {
          "date": "2023-05-01",
          "timestamp": 1682899200000,
          "value": 2.44
        },
        {
          "date": "2023-06-01",
          "timestamp": 1685577600000,
          "value": 2.22
        },
        {
          "date": "2023-07-01",
          "timestamp": 1688169600000,
          "value": 3.45
        },
        {
          "date": "2023-08-01",
          "timestamp": 1690848000000,
          "value": 3.98
        },
        {
          "date": "2023-09-01",
          "timestamp": 1693526400000,
          "value": 2.48
        },
        {
          "date": "2023-10-01",
          "timestamp": 1696118400000,
          "value": 4.5
        },
        {
          "date": "2023-11-01",
          "timestamp": 1698796800000,
          "value": 3.59
        },
        {
          "date": "2023-12-01",
          "timestamp": 1701388800000,
          "value": 4.75
        },
        {
          "date": "2024-01-01",
          "timestamp": 1704067200000,
          "value": 4.3
        },
        {
          "date": "2024-02-01",
          "timestamp": 1706745600000,
          "value": 3.93
        },
        {
          "date": "2024-03-01",
          "timestamp": 1709251200000,
          "value": 4.59
        },
        {
          "date": "2024-04-01",
          "timestamp": 1711929600000,
          "value": 5.23
        },
        {
          "date": "2024-05-01",
          "timestamp": 1714521600000,
          "value": 5.09
        },
        {
          "date": "2024-06-01",
          "timestamp": 1717200000000,
          "value": 4.12
        },
        {
          "date": "2024-07-01",
          "timestamp": 1719792000000,
          "value": 5.65
        },
        {
          "date": "2024-08-01",
          "timestamp": 1722470400000,
          "value": 4.93
        },
        {
          "date": "2024-09-01",
          "timestamp": 1725148800000,
          "value": 5.5
        },
        {
          "date": "2024-10-01",
          "timestamp": 1727740800000,
          "value": 4.93
        },
        {
          "date": "2024-11-01",
          "timestamp": 1730419200000,
          "value": 4.78
        }
      ]
    },
    {
      "series": "CPIAUCSL",
      "name": "Consumer Price Index",
      "unit": "Index 1982-1984=100",
      "frequency": "monthly",
      "startValue": 276,
      "endValue": 310,
      "data": [
        {
          "date": "2021-11-01",
          "timestamp": 1635724800000,
          "value": 275.7
        },
        {
          "date": "2021-12-01",
          "timestamp": 1638316800000,
          "value": 276.07
        },
        {
          "date": "2022-01-01",
          "timestamp": 1640995200000,
          "value": 277.44
        },
        {
          "date": "2022-02-01",
          "timestamp": 1643673600000,
          "value": 278.51
        },
        {
          "date": "2022-03-01",
          "timestamp": 1646092800000,
          "value": 280.01
        },
        {
          "date": "2022-04-01",
          "timestamp": 1648771200000,
          "value": 281.61
        },
        {
          "date": "2022-05-01",
          "timestamp": 1651363200000,
          "value": 280.8
        },
        {
          "date": "2022-06-01",
          "timestamp": 1654041600000,
          "value": 282.98
        },
        {
          "date": "2022-07-01",
          "timestamp": 1656633600000,
          "value": 282.56
        },
        {
          "date": "2022-08-01",
          "timestamp": 1659312000000,
          "value": 284.11
        },
        {
          "date": "2022-09-01",
          "timestamp": 1661990400000,
          "value": 285.28
        },
        {
          "date": "2022-10-01",
          "timestamp": 1664582400000,
          "value": 286.1
        },
        {
          "date": "2022-11-01",
          "timestamp": 1667260800000,
          "value": 286.56
        },
        {
          "date": "2022-12-01",
          "timestamp": 1669852800000,
          "value": 287.78
        },
        {
          "date": "2023-01-01",
          "timestamp": 1672531200000,
          "value": 288.35
        },
        {
          "date": "2023-02-01",
          "timestamp": 1675209600000,
          "value": 289.18
        },
        {
          "date": "2023-03-01",
          "timestamp": 1677628800000,
          "value": 291.72
        },
        {
          "date": "2023-04-01",
          "timestamp": 1680307200000,
          "value": 291.14
        },
        {
          "date": "2023-05-01",
          "timestamp": 1682899200000,
          "value": 292.39
        },
        {
          "date": "2023-06-01",
          "timestamp": 1685577600000,
          "value": 293.48
        },
        {
          "date": "2023-07-01",
          "timestamp": 1688169600000,
          "value": 294.69
        },
        {
          "date": "2023-08-01",
          "timestamp": 1690848000000,
          "value": 296.03
        },
        {
          "date": "2023-09-01",
          "timestamp": 1693526400000,
          "value": 297.17
        },
        {
          "date": "2023-10-01",
          "timestamp": 1696118400000,
          "value": 297.3
        },
        {
          "date": "2023-11-01",
          "timestamp": 1698796800000,
          "value": 298.21
        },
        {
          "date": "2023-12-01",
          "timestamp": 1701388800000,
          "value": 300.6
        },
        {
          "date": "2024-01-01",
          "timestamp": 1704067200000,
          "value": 299.78
        },
        {
          "date": "2024-02-01",
          "timestamp": 1706745600000,
          "value": 300.81
        },
        {
          "date": "2024-03-01",
          "timestamp": 1709251200000,
          "value": 302.66
        },
        {
          "date": "2024-04-01",
          "timestamp": 1711929600000,
          "value": 303.38
        },
        {
          "date": "2024-05-01",
          "timestamp": 1714521600000,
          "value": 303.4
        },
        {
          "date": "2024-06-01",
          "timestamp": 1717200000000,
          "value": 306.16
        },
        {
          "date": "2024-07-01",
          "timestamp": 1719792000000,
          "value": 306.63
        },
        {
          "date": "2024-08-01",
          "timestamp": 1722470400000,
          "value": 308.12
        },
        {
          "date": "2024-09-01",
          "timestamp": 1725148800000,
          "value": 307.38
        },
        {
          "date": "2024-10-01",
          "timestamp": 1727740800000,
          "value": 309.02
        },
        {
          "date": "2024-11-01",
          "timestamp": 1730419200000,
          "value": 310.12
        }
      ]
    },
    {
      "series": "GDP",
      "name": "Gross Domestic Product",
      "unit": "Billions of Dollars",
      "frequency": "quarterly",
      "startValue": 23700,
      "endValue": 27800,
      "data": [
        {
          "date": "2021-11-01",
          "timestamp": 1635724800000,
          "value": 23699.25
        },
        {
          "date": "2022-02-01",
          "timestamp": 1643673600000,
          "value": 23813.19
        },
        {
          "date": "2022-05-01",
          "timestamp": 1651363200000,
          "value": 23927.2
        },
        {
          "date": "2022-08-01",
          "timestamp": 1659312000000,
          "value": 24042.1
        },
        {
          "date": "2022-11-01",
          "timestamp": 1667260800000,
          "value": 24155.93
        },
        {
          "date": "2023-02-01",
          "timestamp": 1675209600000,
          "value": 24269.81
        },
        {
          "date": "2023-05-01",
          "timestamp": 1682899200000,
          "value": 24383.4
        },
        {
          "date": "2023-08-01",
          "timestamp": 1690848000000,
          "value": 24496.62
        },
        {
          "date": "2023-11-01",
          "timestamp": 1698796800000,
          "value": 24612.04
        },
        {
          "date": "2024-02-01",
          "timestamp": 1706745600000,
          "value": 24725.72
        },
        {
          "date": "2024-05-01",
          "timestamp": 1714521600000,
          "value": 24839.69
        },
        {
          "date": "2024-08-01",
          "timestamp": 1722470400000,
          "value": 24952.51
        },
        {
          "date": "2024-11-01",
          "timestamp": 1730419200000,
          "value": 25067.61
        }
      ]
    },
    {
      "series": "UNRATE",
      "name": "Unemployment Rate",
      "unit": "Percent",
      "frequency": "monthly",
      "startValue": 4.2,
      "endValue": 3.8,
      "data": [
        {
          "date": "2021-11-01",
          "timestamp": 1635724800000,
          "value": 4.3
        },
        {
          "date": "2021-12-01",
          "timestamp": 1638316800000,
          "value": 3.4
        },
        {
          "date": "2022-01-01",
          "timestamp": 1640995200000,
          "value": 3.26
        },
        {
          "date": "2022-02-01",
          "timestamp": 1643673600000,
          "value": 3.9
        },
        {
          "date": "2022-03-01",
          "timestamp": 1646092800000,
          "value": 4.37
        },
        {
          "date": "2022-04-01",
          "timestamp": 1648771200000,
          "value": 5.06
        },
        {
          "date": "2022-05-01",
          "timestamp": 1651363200000,
          "value": 4.47
        },
        {
          "date": "2022-06-01",
          "timestamp": 1654041600000,
          "value": 3.77
        },
        {
          "date": "2022-07-01",
          "timestamp": 1656633600000,
          "value": 5.01
        },
        {
          "date": "2022-08-01",
          "timestamp": 1659312000000,
          "value": 3.61
        },
        {
          "date": "2022-09-01",
          "timestamp": 1661990400000,
          "value": 4.74
        },
        {
          "date": "2022-10-01",
          "timestamp": 1664582400000,
          "value": 3.8
        },
        {
          "date": "2022-11-01",
          "timestamp": 1667260800000,
          "value": 4.79
        },
        {
          "date": "2022-12-01",
          "timestamp": 1669852800000,
          "value": 3.58
        },
        {
          "date": "2023-01-01",
          "timestamp": 1672531200000,
          "value": 4.85
        },
        {
          "date": "2023-02-01",
          "timestamp": 1675209600000,
          "value": 3.16
        },
        {
          "date": "2023-03-01",
          "timestamp": 1677628800000,
          "value": 3.32
        },
        {
          "date": "2023-04-01",
          "timestamp": 1680307200000,
          "value": 3.08
        },
        {
          "date": "2023-05-01",
          "timestamp": 1682899200000,
          "value": 3.8
        },
        {
          "date": "2023-06-01",
          "timestamp": 1685577600000,
          "value": 3.71
        },
        {
          "date": "2023-07-01",
          "timestamp": 1688169600000,
          "value": 3.92
        },
        {
          "date": "2023-08-01",
          "timestamp": 1690848000000,
          "value": 4.7
        },
        {
          "date": "2023-09-01",
          "timestamp": 1693526400000,
          "value": 4.34
        },
        {
          "date": "2023-10-01",
          "timestamp": 1696118400000,
          "value": 3.43
        },
        {
          "date": "2023-11-01",
          "timestamp": 1698796800000,
          "value": 3.85
        },
        {
          "date": "2023-12-01",
          "timestamp": 1701388800000,
          "value": 4.63
        },
        {
          "date": "2024-01-01",
          "timestamp": 1704067200000,
          "value": 3.87
        },
        {
          "date": "2024-02-01",
          "timestamp": 1706745600000,
          "value": 4.45
        },
        {
          "date": "2024-03-01",
          "timestamp": 1709251200000,
          "value": 4.6
        },
        {
          "date": "2024-04-01",
          "timestamp": 1711929600000,
          "value": 4.44
        },
        {
          "date": "2024-05-01",
          "timestamp": 1714521600000,
          "value": 3.84
        },
        {
          "date": "2024-06-01",
          "timestamp": 1717200000000,
          "value": 4.28
        },
        {
          "date": "2024-07-01",
          "timestamp": 1719792000000,
          "value": 4.08
        },
        {
          "date": "2024-08-01",
          "timestamp": 1722470400000,
          "value": 3.81
        },
        {
          "date": "2024-09-01",
          "timestamp": 1725148800000,
          "value": 4.29
        },
        {
          "date": "2024-10-01",
          "timestamp": 1727740800000,
          "value": 3.47
        },
        {
          "date": "2024-11-01",
          "timestamp": 1730419200000,
          "value": 3.52
        }
      ]
    },
    {
      "series": "MANEMP",
      "name": "Manufacturing PMI",
      "unit": "Index",
      "frequency": "monthly",
      "startValue": 53,
      "endValue": 48,
      "data": [
        {
          "date": "2021-11-01",
          "timestamp": 1635724800000,
          "value": 52.75
        },
        {
          "date": "2021-12-01",
          "timestamp": 1638316800000,
          "value": 52.57
        },
        {
          "date": "2022-01-01",
          "timestamp": 1640995200000,
          "value": 51.84
        },
        {
          "date": "2022-02-01",
          "timestamp": 1643673600000,
          "value": 51.98
        },
        {
          "date": "2022-03-01",
          "timestamp": 1646092800000,
          "value": 51.91
        },
        {
          "date": "2022-04-01",
          "timestamp": 1648771200000,
          "value": 52.52
        },
        {
          "date": "2022-05-01",
          "timestamp": 1651363200000,
          "value": 52.89
        },
        {
          "date": "2022-06-01",
          "timestamp": 1654041600000,
          "value": 52.19
        },
        {
          "date": "2022-07-01",
          "timestamp": 1656633600000,
          "value": 51.31
        },
        {
          "date": "2022-08-01",
          "timestamp": 1659312000000,
          "value": 51.3
        },
        {
          "date": "2022-09-01",
          "timestamp": 1661990400000,
          "value": 51.58
        },
        {
          "date": "2022-10-01",
          "timestamp": 1664582400000,
          "value": 52.32
        },
        {
          "date": "2022-11-01",
          "timestamp": 1667260800000,
          "value": 50.66
        },
        {
          "date": "2022-12-01",
          "timestamp": 1669852800000,
          "value": 51.75
        },
        {
          "date": "2023-01-01",
          "timestamp": 1672531200000,
          "value": 50.3
        },
        {
          "date": "2023-02-01",
          "timestamp": 1675209600000,
          "value": 51.06
        },
        {
          "date": "2023-03-01",
          "timestamp": 1677628800000,
          "value": 51.38
        },
        {
          "date": "2023-04-01",
          "timestamp": 1680307200000,
          "value": 51.3
        },
        {
          "date": "2023-05-01",
          "timestamp": 1682899200000,
          "value": 50.01
        },
        {
          "date": "2023-06-01",
          "timestamp": 1685577600000,
          "value": 50.59
        },
        {
          "date": "2023-07-01",
          "timestamp": 1688169600000,
          "value": 50.16
        },
        {
          "date": "2023-08-01",
          "timestamp": 1690848000000,
          "value": 51.05
        },
        {
          "date": "2023-09-01",
          "timestamp": 1693526400000,
          "value": 50.88
        },
        {
          "date": "2023-10-01",
          "timestamp": 1696118400000,
          "value": 49.3
        },
        {
          "date": "2023-11-01",
          "timestamp": 1698796800000,
          "value": 49.65
        },
        {
          "date": "2023-12-01",
          "timestamp": 1701388800000,
          "value": 48.57
        },
        {
          "date": "2024-01-01",
          "timestamp": 1704067200000,
          "value": 50.33
        },
        {
          "date": "2024-02-01",
          "timestamp": 1706745600000,
          "value": 49.76
        },
        {
          "date": "2024-03-01",
          "timestamp": 1709251200000,
          "value": 49.39
        },
        {
          "date": "2024-04-01",
          "timestamp": 1711929600000,
          "value": 48.71
        },
        {
          "date": "2024-05-01",
          "timestamp": 1714521600000,
          "value": 48.08
        },
        {
          "date": "2024-06-01",
          "timestamp": 1717200000000,
          "value": 48.3
        },
        {
          "date": "2024-07-01",
          "timestamp": 1719792000000,
          "value": 48.04
        },
        {
          "date": "2024-08-01",
          "timestamp": 1722470400000,
          "value": 48.08
        },
        {
          "date": "2024-09-01",
          "timestamp": 1725148800000,
          "value": 47.37
        },
        {
          "date": "2024-10-01",
          "timestamp": 1727740800000,
          "value": 48.37
        },
        {
          "date": "2024-11-01",
          "timestamp": 1730419200000,
          "value": 47.46
        }
      ]
    }
  ]
}